{"2006-12-01": {"EXPCH": "5015.8", "EXPGE": "3737.6", "EXPMX": "10041.1", "IMPCH": "24109.2", "IMPGE": "7922.9", "IMPMX": "15072.1"}, "2007-01-01": {"EXPCH": "4389.5", "EXPGE": "3618.6", "EXPMX": "10683.5", "IMPCH": "25640.6", "IMPGE": "6853.5", "IMPMX": "15373.4"}, "2007-02-01": {"EXPCH": "4532.9", "EXPGE": "3662.2", "EXPMX": "9980.0", "IMPCH": "23038.9", "IMPGE": "6991.0", "IMPMX": "15142.8"}, "2007-03-01": {"EXPCH": "5425.4", "EXPGE": "4567.3", "EXPMX": "11493.5", "IMPCH": "22723.0", "IMPGE": "8351.8", "IMPMX": "18190.6"}, "2007-04-01": {"EXPCH": "4704.0", "EXPGE": "3975.4", "EXPMX": "10893.2", "IMPCH": "24241.5", "IMPGE": "7858.3", "IMPMX": "16254.9"}, "2007-05-01": {"EXPCH": "5129.4", "EXPGE": "3989.2", "EXPMX": "11956.0", "IMPCH": "25290.6", "IMPGE": "7702.6", "IMPMX": "18018.9"}, "2007-06-01": {"EXPCH": "5561.8", "EXPGE": "4274.6", "EXPMX": "11561.2", "IMPCH": "27071.0", "IMPGE": "7734.2", "IMPMX": "17977.4"}, "2007-07-01": {"EXPCH": "4665.9", "EXPGE": "3835.8", "EXPMX": "11188.7", "IMPCH": "28601.2", "IMPGE": "8384.6", "IMPMX": "16896.9"}, "2007-08-01": {"EXPCH": "5552.8", "EXPGE": "4325.0", "EXPMX": "12282.9", "IMPCH": "28424.5", "IMPGE": "8480.1", "IMPMX": "19115.3"}, "2007-09-01": {"EXPCH": "5311.9", "EXPGE": "4346.1", "EXPMX": "11364.6", "IMPCH": "29419.0", "IMPGE": "7205.4", "IMPMX": "17810.1"}, "2007-10-01": {"EXPCH": "5532.9", "EXPGE": "4522.9", "EXPMX": "12330.2", "IMPCH": "31555.4", "IMPGE": "8486.8", "IMPMX": "19855.8"}, "2007-11-01": {"EXPCH": "5581.5", "EXPGE": "4230.5", "EXPMX": "12127.2", "IMPCH": "29780.7", "IMPGE": "8114.5", "IMPMX": "19356.1"}, "2007-12-01": {"EXPCH": "6548.9", "EXPGE": "4071.9", "EXPMX": "10057.0", "IMPCH": "25656.6", "IMPGE": "8001.3", "IMPMX": "16721.8"}, "2008-01-01": {"EXPCH": "5556.7", "EXPGE": "4064.5", "EXPMX": "11990.6", "IMPCH": "26193.0", "IMPGE": "7078.5", "IMPMX": "17054.5"}, "2008-02-01": {"EXPCH": "5698.1", "EXPGE": "4631.0", "EXPMX": "11961.9", "IMPCH": "24095.9", "IMPGE": "7978.7", "IMPMX": "17674.5"}, "2008-03-01": {"EXPCH": "6294.4", "EXPGE": "4630.2", "EXPMX": "11793.1", "IMPCH": "22440.2", "IMPGE": "9157.4", "IMPMX": "17707.1"}, "2008-04-01": {"EXPCH": "5651.2", "EXPGE": "4760.7", "EXPMX": "12492.9", "IMPCH": "25951.7", "IMPGE": "9217.1", "IMPMX": "19364.9"}, "2008-05-01": {"EXPCH": "6275.7", "EXPGE": "4804.5", "EXPMX": "12297.9", "IMPCH": "27634.5", "IMPGE": "8403.0", "IMPMX": "18837.2"}, "2008-06-01": {"EXPCH": "6188.2", "EXPGE": "4960.0", "EXPMX": "13383.3", "IMPCH": "27930.6", "IMPGE": "8959.1", "IMPMX": "19179.9"}, "2008-07-01": {"EXPCH": "6234.6", "EXPGE": "4747.1", "EXPMX": "13800.8", "IMPCH": "31247.3", "IMPGE": "9229.9", "IMPMX": "19238.0"}, "2008-08-01": {"EXPCH": "6201.3", "EXPGE": "4676.9", "EXPMX": "13749.7", "IMPCH": "31823.7", "IMPGE": "7968.9", "IMPMX": "19522.8"}, "2008-09-01": {"EXPCH": "5257.6", "EXPGE": "4281.0", "EXPMX": "12789.2", "IMPCH": "33078.7", "IMPGE": "7131.9", "IMPMX": "17926.2"}, "2008-10-01": {"EXPCH": "6083.4", "EXPGE": "4763.1", "EXPMX": "14875.5", "IMPCH": "34032.4", "IMPGE": "8084.8", "IMPMX": "19695.7"}, "2008-11-01": {"EXPCH": "5181.0", "EXPGE": "4366.2", "EXPMX": "11944.7", "IMPCH": "28265.0", "IMPGE": "7158.1", "IMPMX": "15471.6"}, "2008-12-01": {"EXPCH": "5110.7", "EXPGE": "3820.3", "EXPMX": "10140.5", "IMPCH": "25079.5", "IMPGE": "7129.2", "IMPMX": "14269.1"}, "2009-01-01": {"EXPCH": "4159.6", "EXPGE": "3555.6", "EXPMX": "9781.1", "IMPCH": "24743.5", "IMPGE": "5213.6", "IMPMX": "12464.9"}, "2009-02-01": {"EXPCH": "4661.7", "EXPGE": "3798.2", "EXPMX": "9262.5", "IMPCH": "18845.5", "IMPGE": "5640.1", "IMPMX": "12379.8"}, "2009-03-01": {"EXPCH": "5579.3", "EXPGE": "3771.2", "EXPMX": "10024.7", "IMPCH": "21224.7", "IMPGE": "5948.8", "IMPMX": "13929.6"}, "2009-04-01": {"EXPCH": "5161.4", "EXPGE": "3223.3", "EXPMX": "9571.4", "IMPCH": "21920.6", "IMPGE": "5458.0", "IMPMX": "13715.7"}, "2009-05-01": {"EXPCH": "5256.0", "EXPGE": "3656.2", "EXPMX": "9397.6", "IMPCH": "22734.1", "IMPGE": "4932.8", "IMPMX": "13317.5"}, "2009-06-01": {"EXPCH": "5548.6", "EXPGE": "3181.3", "EXPMX": "10546.9", "IMPCH": "23972.8", "IMPGE": "5513.5", "IMPMX": "14011.5"}, "2009-07-01": {"EXPCH": "5269.3", "EXPGE": "3285.1", "EXPMX": "11130.9", "IMPCH": "25671.1", "IMPGE": "6539.2", "IMPMX": "14081.7"}, "2009-08-01": {"EXPCH": "5518.0", "EXPGE": "3467.9", "EXPMX": "11072.4", "IMPCH": "25798.1", "IMPGE": "5775.1", "IMPMX": "15060.5"}, "2009-09-01": {"EXPCH": "5764.3", "EXPGE": "3633.3", "EXPMX": "11576.5", "IMPCH": "27893.9", "IMPGE": "5670.6", "IMPMX": "16130.0"}, "2009-10-01": {"EXPCH": "6879.3", "EXPGE": "4103.7", "EXPMX": "12731.0", "IMPCH": "29557.8", "IMPGE": "6894.2", "IMPMX": "17289.9"}, "2009-11-01": {"EXPCH": "7374.2", "EXPGE": "3608.7", "EXPMX": "12013.6", "IMPCH": "27541.7", "IMPGE": "6948.5", "IMPMX": "17185.8"}, "2009-12-01": {"EXPCH": "8325.0", "EXPGE": "4021.6", "EXPMX": "11783.4", "IMPCH": "26470.1", "IMPGE": "6963.9", "IMPMX": "17087.5"}, "2010-01-01": {"EXPCH": "6898.4", "EXPGE": "3826.7", "EXPMX": "11522.3", "IMPCH": "25215.9", "IMPGE": "5007.7", "IMPMX": "16089.4"}, "2010-02-01": {"EXPCH": "6840.2", "EXPGE": "3488.0", "EXPMX": "11715.4", "IMPCH": "23342.8", "IMPGE": "5750.2", "IMPMX": "16459.3"}, "2010-03-01": {"EXPCH": "7400.8", "EXPGE": "4242.6", "EXPMX": "14201.4", "IMPCH": "24292.2", "IMPGE": "7204.8", "IMPMX": "20089.5"}, "2010-04-01": {"EXPCH": "6600.7", "EXPGE": "3686.3", "EXPMX": "13248.7", "IMPCH": "25920.2", "IMPGE": "6678.9", "IMPMX": "18594.2"}, "2010-05-01": {"EXPCH": "6755.3", "EXPGE": "3799.0", "EXPMX": "13279.3", "IMPCH": "29052.4", "IMPGE": "6795.2", "IMPMX": "19419.2"}, "2010-06-01": {"EXPCH": "6733.7", "EXPGE": "4118.1", "EXPMX": "13891.8", "IMPCH": "32843.1", "IMPGE": "6798.5", "IMPMX": "20049.1"}, "2010-07-01": {"EXPCH": "7339.3", "EXPGE": "3790.5", "EXPMX": "13210.3", "IMPCH": "33266.8", "IMPGE": "7245.4", "IMPMX": "18213.8"}, "2010-08-01": {"EXPCH": "7209.7", "EXPGE": "4057.4", "EXPMX": "14177.6", "IMPCH": "35375.3", "IMPGE": "7479.6", "IMPMX": "20252.2"}, "2010-09-01": {"EXPCH": "7114.3", "EXPGE": "4108.0", "EXPMX": "13953.4", "IMPCH": "35196.7", "IMPGE": "6767.0", "IMPMX": "19908.0"}, "2010-10-01": {"EXPCH": "9417.3", "EXPGE": "4374.1", "EXPMX": "14905.5", "IMPCH": "35083.3", "IMPGE": "7692.0", "IMPMX": "21024.0"}, "2010-11-01": {"EXPCH": "9475.8", "EXPGE": "4567.3", "EXPMX": "14915.7", "IMPCH": "34564.3", "IMPGE": "7699.8", "IMPMX": "20530.3"}, "2010-12-01": {"EXPCH": "10125.6", "EXPGE": "4097.3", "EXPMX": "14643.3", "IMPCH": "30799.6", "IMPGE": "7331.4", "IMPMX": "19356.7"}, "2011-01-01": {"EXPCH": "8017.8", "EXPGE": "3688.7", "EXPMX": "14850.3", "IMPCH": "31377.4", "IMPGE": "6997.8", "IMPMX": "19606.4"}, "2011-02-01": {"EXPCH": "8383.3", "EXPGE": "3846.2", "EXPMX": "13908.7", "IMPCH": "27244.7", "IMPGE": "7023.6", "IMPMX": "19053.6"}, "2011-03-01": {"EXPCH": "9563.7", "EXPGE": "4394.4", "EXPMX": "17337.9", "IMPCH": "27599.7", "IMPGE": "9065.0", "IMPMX": "23269.5"}, "2011-04-01": {"EXPCH": "8000.5", "EXPGE": "4187.3", "EXPMX": "16032.6", "IMPCH": "29580.3", "IMPGE": "8030.8", "IMPMX": "21359.7"}, "2011-05-01": {"EXPCH": "7849.2", "EXPGE": "4083.3", "EXPMX": "16811.8", "IMPCH": "32788.1", "IMPGE": "7864.2", "IMPMX": "22970.2"}, "2011-06-01": {"EXPCH": "7867.0", "EXPGE": "4378.4", "EXPMX": "16792.8", "IMPCH": "34374.8", "IMPGE": "8086.2", "IMPMX": "22714.8"}, "2011-07-01": {"EXPCH": "8157.9", "EXPGE": "3641.4", "EXPMX": "16045.4", "IMPCH": "35152.2", "IMPGE": "7954.0", "IMPMX": "21091.3"}, "2011-08-01": {"EXPCH": "8421.6", "EXPGE": "4263.7", "EXPMX": "17764.2", "IMPCH": "37374.1", "IMPGE": "8843.6", "IMPMX": "23152.5"}, "2011-09-01": {"EXPCH": "8370.1", "EXPGE": "4015.6", "EXPMX": "17095.3", "IMPCH": "36418.6", "IMPGE": "8188.9", "IMPMX": "22303.5"}, "2011-10-01": {"EXPCH": "9745.6", "EXPGE": "4505.4", "EXPMX": "17633.0", "IMPCH": "37824.1", "IMPGE": "8704.8", "IMPMX": "22853.7"}, "2011-11-01": {"EXPCH": "9997.2", "EXPGE": "4223.9", "EXPMX": "17664.3", "IMPCH": "36764.9", "IMPGE": "8864.1", "IMPMX": "23146.8"}, "2011-12-01": {"EXPCH": "9747.7", "EXPGE": "4065.8", "EXPMX": "16352.3", "IMPCH": "32872.3", "IMPGE": "9061.5", "IMPMX": "21351.7"}, "2012-01-01": {"EXPCH": "8359.5", "EXPGE": "3666.4", "EXPMX": "17011.2", "IMPCH": "34417.5", "IMPGE": "7693.9", "IMPMX": "21503.9"}, "2012-02-01": {"EXPCH": "8785.7", "EXPGE": "4189.6", "EXPMX": "16935.9", "IMPCH": "28105.2", "IMPGE": "7933.3", "IMPMX": "22617.2"}, "2012-03-01": {"EXPCH": "9811.6", "EXPGE": "4599.2", "EXPMX": "19006.9", "IMPCH": "31431.3", "IMPGE": "10209.4", "IMPMX": "25115.0"}, "2012-04-01": {"EXPCH": "8468.1", "EXPGE": "4183.1", "EXPMX": "17208.6", "IMPCH": "33016.3", "IMPGE": "8867.7", "IMPMX": "22757.4"}, "2012-05-01": {"EXPCH": "8960.2", "EXPGE": "4226.6", "EXPMX": "18426.9", "IMPCH": "34937.8", "IMPGE": "9014.8", "IMPMX": "24815.0"}, "2012-06-01": {"EXPCH": "8478.1", "EXPGE": "4246.6", "EXPMX": "17476.0", "IMPCH": "35949.4", "IMPGE": "8462.6", "IMPMX": "23513.9"}, "2012-07-01": {"EXPCH": "8515.1", "EXPGE": "3628.8", "EXPMX": "17539.9", "IMPCH": "37930.8", "IMPGE": "9116.0", "IMPMX": "22526.3"}, "2012-08-01": {"EXPCH": "8613.3", "EXPGE": "4053.8", "EXPMX": "19219.0", "IMPCH": "37280.6", "IMPGE": "9729.5", "IMPMX": "23763.8"}, "2012-09-01": {"EXPCH": "8804.2", "EXPGE": "4156.5", "EXPMX": "17457.4", "IMPCH": "37891.8", "IMPGE": "8951.3", "IMPMX": "22151.1"}, "2012-10-01": {"EXPCH": "10824.4", "EXPGE": "4116.8", "EXPMX": "20453.8", "IMPCH": "40257.1", "IMPGE": "9664.7", "IMPMX": "24817.6"}, "2012-11-01": {"EXPCH": "10587.8", "EXPGE": "3934.2", "EXPMX": "18764.0", "IMPCH": "39543.7", "IMPGE": "10180.1", "IMPMX": "23731.3"}, "2012-12-01": {"EXPCH": "10308.6", "EXPGE": "3801.4", "EXPMX": "16375.4", "IMPCH": "34857.6", "IMPGE": "9402.5", "IMPMX": "20281.1"}, "2013-01-01": {"EXPCH": "9382.9", "EXPGE": "3788.5", "EXPMX": "17902.5", "IMPCH": "37193.7", "IMPGE": "7722.9", "IMPMX": "21555.7"}, "2013-02-01": {"EXPCH": "9133.3", "EXPGE": "3841.9", "EXPMX": "17703.2", "IMPCH": "32742.7", "IMPGE": "8520.3", "IMPMX": "22070.2"}, "2013-03-01": {"EXPCH": "9539.0", "EXPGE": "4412.7", "EXPMX": "18092.7", "IMPCH": "27294.1", "IMPGE": "9714.0", "IMPMX": "23152.3"}, "2013-04-01": {"EXPCH": "8954.0", "EXPGE": "3795.4", "EXPMX": "19794.6", "IMPCH": "33131.9", "IMPGE": "9767.2", "IMPMX": "24364.1"}, "2013-05-01": {"EXPCH": "8752.8", "EXPGE": "4024.4", "EXPMX": "19226.2", "IMPCH": "36617.6", "IMPGE": "9629.0", "IMPMX": "24484.3"}, "2013-06-01": {"EXPCH": "9217.6", "EXPGE": "3899.9", "EXPMX": "17986.3", "IMPCH": "35886.0", "IMPGE": "8794.8", "IMPMX": "22927.6"}, "2013-07-01": {"EXPCH": "8723.7", "EXPGE": "3616.4", "EXPMX": "19581.8", "IMPCH": "38800.4", "IMPGE": "9970.3", "IMPMX": "23545.9"}, "2013-08-01": {"EXPCH": "9352.1", "EXPGE": "4163.4", "EXPMX": "19191.1", "IMPCH": "39161.3", "IMPGE": "9490.9", "IMPMX": "23988.3"}, "2013-09-01": {"EXPCH": "9527.2", "EXPGE": "3751.6", "EXPMX": "18023.0", "IMPCH": "40144.4", "IMPGE": "10038.5", "IMPMX": "23303.3"}, "2013-10-01": {"EXPCH": "13147.8", "EXPGE": "4045.5", "EXPMX": "21065.3", "IMPCH": "41845.5", "IMPGE": "10884.5", "IMPMX": "25314.9"}, "2013-11-01": {"EXPCH": "13027.1", "EXPGE": "4394.8", "EXPMX": "19290.4", "IMPCH": "40112.3", "IMPGE": "10384.0", "IMPMX": "23723.3"}, "2013-12-01": {"EXPCH": "12988.7", "EXPGE": "3629.0", "EXPMX": "18097.2", "IMPCH": "37500.2", "IMPGE": "9425.6", "IMPMX": "22126.1"}, "2014-01-01": {"EXPCH": "10262.9", "EXPGE": "3836.2", "EXPMX": "19122.5", "IMPCH": "38377.8", "IMPGE": "9129.5", "IMPMX": "22021.4"}, "2014-02-01": {"EXPCH": "9752.9", "EXPGE": "4311.5", "EXPMX": "18444.0", "IMPCH": "30700.3", "IMPGE": "8909.8", "IMPMX": "22445.2"}, "2014-03-01": {"EXPCH": "10936.2", "EXPGE": "4646.8", "EXPMX": "19964.2", "IMPCH": "31420.7", "IMPGE": "10689.1", "IMPMX": "24943.7"}, "2014-04-01": {"EXPCH": "9029.5", "EXPGE": "4092.2", "EXPMX": "19847.5", "IMPCH": "36450.5", "IMPGE": "11073.9", "IMPMX": "24577.8"}, "2014-05-01": {"EXPCH": "9221.3", "EXPGE": "4060.6", "EXPMX": "20998.4", "IMPCH": "38188.6", "IMPGE": "10840.3", "IMPMX": "25444.7"}, "2014-06-01": {"EXPCH": "9333.9", "EXPGE": "4371.1", "EXPMX": "20087.3", "IMPCH": "39606.2", "IMPGE": "9732.4", "IMPMX": "25134.2"}, "2014-07-01": {"EXPCH": "9292.9", "EXPGE": "3966.1", "EXPMX": "20770.0", "IMPCH": "40323.4", "IMPGE": "10502.9", "IMPMX": "25308.8"}, "2014-08-01": {"EXPCH": "9626.7", "EXPGE": "4224.0", "EXPMX": "20335.6", "IMPCH": "40093.0", "IMPGE": "11339.3", "IMPMX": "24849.7"}, "2014-09-01": {"EXPCH": "9315.0", "EXPGE": "4077.1", "EXPMX": "20007.0", "IMPCH": "45104.5", "IMPGE": "10269.7", "IMPMX": "25032.9"}, "2014-10-01": {"EXPCH": "12565.8", "EXPGE": "3975.9", "EXPMX": "22306.8", "IMPCH": "45334.5", "IMPGE": "10930.8", "IMPMX": "27563.7"}, "2014-11-01": {"EXPCH": "12128.0", "EXPGE": "4002.4", "EXPMX": "19662.3", "IMPCH": "42484.2", "IMPGE": "10565.8", "IMPMX": "24384.1"}, "2014-12-01": {"EXPCH": "12155.5", "EXPGE": "3806.5", "EXPMX": "18785.7", "IMPCH": "40400.3", "IMPGE": "10195.5", "IMPMX": "24033.2"}, "2015-01-01": {"EXPCH": "9481.5", "EXPGE": "3751.8", "EXPMX": "19100.7", "IMPCH": "38588.4", "IMPGE": "9311.2", "IMPMX": "22256.0"}, "2015-02-01": {"EXPCH": "8759.3", "EXPGE": "4072.0", "EXPMX": "18108.6", "IMPCH": "31573.6", "IMPGE": "9354.5", "IMPMX": "22711.8"}, "2015-03-01": {"EXPCH": "9882.0", "EXPGE": "4668.5", "EXPMX": "19835.7", "IMPCH": "41139.2", "IMPGE": "10853.7", "IMPMX": "25648.4"}, "2015-04-01": {"EXPCH": "9306.7", "EXPGE": "4276.5", "EXPMX": "19998.4", "IMPCH": "36115.8", "IMPGE": "10830.7", "IMPMX": "24701.8"}, "2015-05-01": {"EXPCH": "8763.1", "EXPGE": "4030.9", "EXPMX": "19606.6", "IMPCH": "39073.2", "IMPGE": "10206.2", "IMPMX": "24482.9"}, "2015-06-01": {"EXPCH": "9621.7", "EXPGE": "4065.5", "EXPMX": "20448.7", "IMPCH": "41455.0", "IMPGE": "10557.1", "IMPMX": "26920.6"}, "2015-07-01": {"EXPCH": "9513.6", "EXPGE": "4069.5", "EXPMX": "21074.3", "IMPCH": "41216.4", "IMPGE": "10693.8", "IMPMX": "24784.2"}, "2015-08-01": {"EXPCH": "9169.3", "EXPGE": "3921.4", "EXPMX": "19536.7", "IMPCH": "44141.9", "IMPGE": "10926.1", "IMPMX": "24695.7"}, "2015-09-01": {"EXPCH": "9424.3", "EXPGE": "4252.7", "EXPMX": "19486.1", "IMPCH": "45718.2", "IMPGE": "9815.1", "IMPMX": "25330.3"}, "2015-10-01": {"EXPCH": "11410.1", "EXPGE": "4750.2", "EXPMX": "21163.6", "IMPCH": "44318.6", "IMPGE": "11373.6", "IMPMX": "27672.0"}, "2015-11-01": {"EXPCH": "10618.0", "EXPGE": "4110.3", "EXPMX": "18869.0", "IMPCH": "41908.3", "IMPGE": "10175.9", "IMPMX": "24050.2"}, "2015-12-01": {"EXPCH": "10122.3", "EXPGE": "4001.5", "EXPMX": "18516.8", "IMPCH": "37996.2", "IMPGE": "10722.6", "IMPMX": "23154.0"}, "2016-01-01": {"EXPCH": "8212.1", "EXPGE": "3697.3", "EXPMX": "18065.8", "IMPCH": "37145.7", "IMPGE": "8239.4", "IMPMX": "22400.7"}, "2016-02-01": {"EXPCH": "8048.7", "EXPGE": "4188.3", "EXPMX": "18226.3", "IMPCH": "36160.8", "IMPGE": "8698.0", "IMPMX": "23191.8"}, "2016-03-01": {"EXPCH": "8952.3", "EXPGE": "4419.3", "EXPMX": "19338.8", "IMPCH": "29852.7", "IMPGE": "10821.9", "IMPMX": "24744.1"}, "2016-04-01": {"EXPCH": "8667.1", "EXPGE": "3997.6", "EXPMX": "19385.1", "IMPCH": "32973.2", "IMPGE": "9865.6", "IMPMX": "25098.4"}, "2016-05-01": {"EXPCH": "8518.3", "EXPGE": "4078.0", "EXPMX": "19040.6", "IMPCH": "37535.2", "IMPGE": "9771.3", "IMPMX": "24842.5"}, "2016-06-01": {"EXPCH": "8822.7", "EXPGE": "3973.9", "EXPMX": "19556.3", "IMPCH": "38579.0", "IMPGE": "9418.0", "IMPMX": "24906.6"}, "2016-07-01": {"EXPCH": "9156.9", "EXPGE": "4003.1", "EXPMX": "18303.7", "IMPCH": "39487.1", "IMPGE": "9387.1", "IMPMX": "23025.9"}, "2016-08-01": {"EXPCH": "9393.9", "EXPGE": "4175.5", "EXPMX": "20282.6", "IMPCH": "43247.3", "IMPGE": "10216.7", "IMPMX": "25557.2"}, "2016-09-01": {"EXPCH": "9559.9", "EXPGE": "4309.6", "EXPMX": "19845.8", "IMPCH": "42022.7", "IMPGE": "9331.5", "IMPMX": "25089.1"}, "2016-10-01": {"EXPCH": "12698.0", "EXPGE": "4274.1", "EXPMX": "20211.4", "IMPCH": "43807.1", "IMPGE": "9261.6", "IMPMX": "26405.4"}, "2016-11-01": {"EXPCH": "12119.3", "EXPGE": "3881.2", "EXPMX": "19592.5", "IMPCH": "42620.5", "IMPGE": "9542.7", "IMPMX": "25385.5"}, "2016-12-01": {"EXPCH": "11626.0", "EXPGE": "4364.2", "EXPMX": "19110.4", "IMPCH": "39381.8", "IMPGE": "9673.5", "IMPMX": "23503.8"}}